snowsignal/__init__.py
snowsignal/__main__.py
snowsignal/configure.py
snowsignal/dockerfile
snowsignal/netutils.py
snowsignal/packet.py
snowsignal/pva_packet.py
snowsignal/snowsignal.py
snowsignal/udp_relay_receive.py
snowsignal/udp_relay_transmit.py
snowsignal-0.1.4.2.dist-info/METADATA
snowsignal-0.1.4.2.dist-info/WHEEL
snowsignal-0.1.4.2.dist-info/licenses/LICENSE
snowsignal-0.1.4.2.dist-info/RECORD
