Metadata-Version: 2.4
Name: SnowSignal
Version: 0.1.4.2
Summary: UDP Broadcast Relay
Project-URL: Repository, https://github.com/ISISNeutronMuon/SnowSignal
Author-email: Ivan Finch <ivan.finch@stfc.ac.uk>
Maintainer-email: Ivan Finch <ivan.finch@stfc.ac.uk>
License-File: LICENSE
Keywords: UDP,UDP broadcast,docker swarm,epics,pvaccess
Classifier: Development Status :: 4 - Beta
Classifier: Environment :: Console
Classifier: Intended Audience :: System Administrators
Classifier: License :: OSI Approved :: BSD License
Classifier: Operating System :: POSIX :: Linux
Classifier: Programming Language :: Python
Classifier: Topic :: System :: Networking
Classifier: Typing :: Typed
Requires-Python: >=3.11
Requires-Dist: cachetools>=5.5
Requires-Dist: configargparse>=1.7
Requires-Dist: psutil>=5.9
Provides-Extra: dist
Requires-Dist: build>=1.2; extra == 'dist'
Requires-Dist: hatch>=1.14; extra == 'dist'
Provides-Extra: test
Requires-Dist: coverage>=7.6; extra == 'test'
Requires-Dist: ruff>0.9; extra == 'test'
Requires-Dist: scapy~=2.0; extra == 'test'
